py_eth_sig_utils/__init__.py
py_eth_sig_utils/signing.py
py_eth_sig_utils/utils.py
py_eth_sig_utils/eip712/__init__.py
py_eth_sig_utils/eip712/encoding.py
py_eth_sig_utils/tests/__init__.py
py_eth_sig_utils/tests/test_eip712_encode.py
py_eth_sig_utils/tests/test_sign_typed_data.py
py_eth_sig_utils-0.4.0.dist-info/LICENSE
py_eth_sig_utils-0.4.0.dist-info/METADATA
py_eth_sig_utils-0.4.0.dist-info/WHEEL
py_eth_sig_utils-0.4.0.dist-info/top_level.txt
py_eth_sig_utils-0.4.0.dist-info/RECORD
