Metadata-Version: 2.1
Name: py-eth-sig-utils
Version: 0.4.0
Summary: Python Ethereum Signing Utils
Home-page: https://github.com/rmeissner/py-eth-sig-utils
Author: Richard Meissner
Author-email: msc.meissner@gmail.com
License: MIT License
Platform: Any
Classifier: Programming Language :: Python :: 3
Classifier: License :: OSI Approved :: MIT License
Classifier: Operating System :: OS Independent
Provides-Extra: dev
